{"levels":[{"iVolume":103,"iTurover":33.8200000000002,"time":"20171127162037","levelIndex":"5","leveltype":1},{"iVolume":4,"iTurover":33.8400000000001,"time":"20171127162037","levelIndex":"5","leveltype":2},{"iVolume":89,"iTurover":33.8099999999999,"time":"20171127162037","levelIndex":"5","leveltype":1},{"iVolume":6,"iTurover":33.8499999999999,"time":"20171127162037","levelIndex":"5","leveltype":2},{"iVolume":57,"iTurover":33.8000000000002,"time":"20171127162037","levelIndex":"5","leveltype":1},{"iVolume":22,"iTurover":33.8600000000001,"time":"20171127162037","levelIndex":"5","leveltype":2},{"iVolume":61,"iTurover":33.79,"time":"20171127162037","levelIndex":"5","leveltype":1},{"iVolume":42,"iTurover":33.8699999999999,"time":"20171127162037","levelIndex":"5","leveltype":2},{"iVolume":5555,"iTurover":33.7800000000002,"time":"20171127162037","levelIndex":"5","leveltype":1},{"iVolume":41,"iTurover":33.8800000000001,"time":"20171127162037","levelIndex":"5","leveltype":2}]}
